{"dialog_text_Flan":{"Active":true,"DialogFile":"dialog_text_Flan","AddOn":[{"DialogID":60000,"LineID":0,"FaceSprite":"Flan0a","Dialog":"I'll rip you to shreds!"},{"DialogID":60000,"LineID":1,"FaceSprite":"Flan1a","Dialog":"Ehehe... Gotcha."},{"DialogID":60000,"LineID":2,"FaceSprite":"Flan1a","Dialog":"Smash!"},{"DialogID":60001,"LineID":0,"FaceSprite":"Flan0a","Dialog":"You can't run from me."},{"DialogID":60001,"LineID":1,"FaceSprite":"Flan1a","Dialog":"See... I caught you."},{"DialogID":60001,"LineID":2,"FaceSprite":"Flan1a","Dialog":"Break!"},{"DialogID":60002,"LineID":0,"FaceSprite":"Flan0a","Dialog":"All right, I have you cornered now!"},{"DialogID":60002,"LineID":1,"FaceSprite":"Flan1a","Dialog":"Hehe... Are you ready?"},{"DialogID":60002,"LineID":2,"FaceSprite":"Flan1a","Dialog":"Disappear!"},{"DialogID":60003,"LineID":0,"FaceSprite":"Flan0a","Dialog":"I'll smash you up... all of you."},{"DialogID":60004,"LineID":0,"FaceSprite":"Flan1a","Dialog":"You're all out of line!"},{"DialogID":60005,"LineID":0,"FaceSprite":"Flan1a","Dialog":"You're scared of me, I know!"}]}}